cyberpunk_theme/__init__.py
cyberpunk_theme/__main__.py
cyberpunk_theme/constant.py
cyberpunk_theme/hooking/__init__.py
cyberpunk_theme/hooking/ante_build_hook.py
cyberpunk_theme/hooking/ante_release_hook.py
cyberpunk_theme/hooking/post_build_hook.py
cyberpunk_theme/hooking/post_release_hook.py
cyberpunk_theme/megawidget/__init__.py
cyberpunk_theme/megawidget/choice.py
cyberpunk_theme/megawidget/confirm.py
cyberpunk_theme/megawidget/confirmation.py
cyberpunk_theme/megawidget/pathentry.py
cyberpunk_theme/megawidget/pathfield.py
cyberpunk_theme/megawidget/scrollbox.py
cyberpunk_theme/megawidget/table.py
cyberpunk_theme/megawidget/toast.py
cyberpunk_theme/megawidget/tree.py
cyberpunk_theme/pyrustic_data/build_report.json
cyberpunk_theme/pyrustic_data/hooking.json
cyberpunk_theme/pyrustic_data/hubstore.json
cyberpunk_theme/pyrustic_data/release_info.json
cyberpunk_theme/pyrustic_data/backstage/config/build.json
cyberpunk_theme/pyrustic_data/backstage/config/init.json
cyberpunk_theme/pyrustic_data/backstage/config/release.json
cyberpunk_theme/pyrustic_data/backstage/data/build_report.json
cyberpunk_theme/pyrustic_data/backstage/data/github_release_form.json
cyberpunk_theme/pyrustic_data/backstage/hooking/build.json
cyberpunk_theme/pyrustic_data/backstage/hooking/init.json
cyberpunk_theme/pyrustic_data/backstage/hooking/release.json
cyberpunk_theme/pyrustic_data/backstage/report/build_report.json
cyberpunk_theme/pyrustic_data/backstage/report/release_report.json
cyberpunk_theme/pyrustic_data/hubstore/img.json
cyberpunk_theme/pyrustic_data/hubstore/promotion.json
cyberpunk_theme/widget/__init__.py
cyberpunk_theme/widget/button.py
cyberpunk_theme/widget/canvas.py
cyberpunk_theme/widget/checkbutton.py
cyberpunk_theme/widget/entry.py
cyberpunk_theme/widget/frame.py
cyberpunk_theme/widget/label.py
cyberpunk_theme/widget/label_frame.py
cyberpunk_theme/widget/listbox.py
cyberpunk_theme/widget/menu.py
cyberpunk_theme/widget/menubutton.py
cyberpunk_theme/widget/option_menu.py
cyberpunk_theme-0.0.14.dist-info/LICENSE
cyberpunk_theme-0.0.14.dist-info/METADATA
cyberpunk_theme-0.0.14.dist-info/WHEEL
cyberpunk_theme-0.0.14.dist-info/entry_points.txt
cyberpunk_theme-0.0.14.dist-info/top_level.txt
cyberpunk_theme-0.0.14.dist-info/RECORD
