Metadata-Version: 2.1
Name: cyberpunk-theme
Version: 0.0.14
Summary: Dark theme for Python desktop apps
Home-page: https://github.com/pyrustic/cyberpunk-theme
Author: Pyrustic Evangelist
Author-email: rusticalex@yahoo.com
Maintainer: Pyrustic Evangelist
Maintainer-email: rusticalex@yahoo.com
License: MIT
Keywords: theme,cyberpunk,dark-theme,tkstyle,tkinter,gui,beautiful,frontend,app,pyrustic,desktop-application
Platform: UNKNOWN
Classifier: Programming Language :: Python :: 3
Classifier: License :: OSI Approved :: MIT License
Classifier: Operating System :: OS Independent
Requires-Python: >=3.5
License-File: LICENSE
Requires-Dist: tkstyle
